EZMotionMMS2/EZMotionMMS2.py
EZMotionMMS2/Example_Homing_mode.py
EZMotionMMS2/Example_Position_mode.py
EZMotionMMS2/Example_Speed_mode.py
EZMotionMMS2/Example_Torque_mode.py
EZMotionMMS2/__init__.py
EZMotionMMS2-1.0.2.dist-info/METADATA
EZMotionMMS2-1.0.2.dist-info/WHEEL
EZMotionMMS2-1.0.2.dist-info/top_level.txt
EZMotionMMS2-1.0.2.dist-info/RECORD
