Metadata-Version: 2.1
Name: EZMotionMMS2
Version: 1.0.2
Summary: Python wrapper built around minimalmodbus for controlling EZMotion MMP/ MMS 740 and 760 series servo motors and driver modules via serial-to-RS485 converter.
Home-page: https://github.com/EZmotionTechnologies/Python_API_EZM2
Author: Charan Bhamra
Author-email: charan.bhamra@ezmotion.co
Requires-Dist: setuptools >=42
Requires-Dist: pyserial >=3.0
Requires-Dist: numpy >=1.21.6
Requires-Dist: minimalmodbus >=2.0.1
